bepatient_db/__init__.py
bepatient_db/api.py
bepatient_db/sql_checkers.py
bepatient_db/sql_executor.py
bepatient_db-0.4.0.dist-info/LICENSE
bepatient_db-0.4.0.dist-info/METADATA
bepatient_db-0.4.0.dist-info/WHEEL
bepatient_db-0.4.0.dist-info/top_level.txt
bepatient_db-0.4.0.dist-info/RECORD
