Metadata-Version: 2.1
Name: bepatient-db
Version: 0.4.0
Summary: Plugin for the 'bepatient' library adding database support.
Author-email: Dawid Szaniawski <webluduspl@gmail.com>
License: MIT License
Project-URL: Source, https://github.com/dawid-szaniawski/bepatient-db
Keywords: api,async,api_testing,automation,database,json,mySQL,postgreSQL,SQL,SQLite,testing,web
Classifier: Development Status :: 3 - Alpha
Classifier: Environment :: Web Environment
Classifier: Intended Audience :: Developers
Classifier: Natural Language :: English
Classifier: Operating System :: OS Independent
Classifier: License :: OSI Approved :: MIT License
Classifier: Programming Language :: Python
Classifier: Programming Language :: Python :: 3.10
Classifier: Programming Language :: Python :: 3.11
Classifier: Programming Language :: Python :: 3.12
Classifier: Programming Language :: Python :: 3 :: Only
Classifier: Programming Language :: Python :: Implementation :: CPython
Classifier: Topic :: Internet :: WWW/HTTP
Classifier: Topic :: Software Development :: Libraries
Classifier: Topic :: Software Development :: Testing
Classifier: Topic :: Software Development :: Quality Assurance
Classifier: Topic :: Utilities
Classifier: Topic :: File Formats :: JSON
Classifier: Topic :: File Formats :: JSON :: JSON Schema
Classifier: Typing :: Typed
Classifier: Topic :: Database
Classifier: Topic :: Database :: Database Engines/Servers
Classifier: Programming Language :: SQL
Requires-Python: >=3.10
License-File: LICENSE
Requires-Dist: bepatient>=0.10.2
Requires-Dist: dictor>=0.1.12
Requires-Dist: mysql-connector-python~=8.1.0
Requires-Dist: psycopg2-binary~=2.9.7
Provides-Extra: dev
Requires-Dist: black>=24.8.0; extra == "dev"
Requires-Dist: flake8>=7.1.1; extra == "dev"
Requires-Dist: isort>=5.13.2; extra == "dev"
Requires-Dist: mypy>=1.11.1; extra == "dev"
Requires-Dist: pylint>=3.2.6; extra == "dev"
Requires-Dist: pytest>=8.3.2; extra == "dev"
Requires-Dist: pytest-cov>=5.0.0; extra == "dev"
Requires-Dist: pytest-mock>=3.14.0; extra == "dev"
Requires-Dist: ruff>=0.5.7; extra == "dev"
Requires-Dist: tox>=4.17.1; extra == "dev"
Requires-Dist: twine>=5.1.1; extra == "dev"
Provides-Extra: docs
Requires-Dist: mkdocs-material>=9.5.31; extra == "docs"
Requires-Dist: mkdocs-minify-plugin>=0.8.0; extra == "docs"
